ironpython/__init__.py
ironpython/ironpython.py
ironpython-1.0.dist-info/METADATA
ironpython-1.0.dist-info/WHEEL
ironpython-1.0.dist-info/licenses/LICENSE.txt
ironpython-1.0.dist-info/RECORD
