Metadata-Version: 2.3
Name: ironpython
Version: 1.0
Summary: IronPython is an open-source implementation of the Python programming language which is tightly integrated with .NET
Author-email: Joseph Spracklen <joseph.spracklen@my.utsa.edu>
License-File: LICENSE.txt
Classifier: License :: OSI Approved :: MIT License
Classifier: Operating System :: OS Independent
Classifier: Programming Language :: Python :: 3
Requires-Python: >=3.8
